Metadata-Version: 2.1
Name: ColabAudioProcessing
Version: 1.2
Summary: Implementación para el análisis y modificacion de archvos .wav en Google Colaboratory/iPython
Home-page: https://github.com/DarkNightSoldier/ColabAudioProcessing
Author: Alejandro Higuera
Author-email: ahiguerac@unal.edu.co
License: MIT
Keywords: Manipulation,Spanish,Audio,WAVFILE
Platform: UNKNOWN
Classifier: Programming Language :: Python :: 3
Classifier: License :: OSI Approved :: BSD License
Classifier: Operating System :: OS Independent
Classifier: Intended Audience :: Science/Research
Classifier: Topic :: Education
Classifier: Topic :: Scientific/Engineering
